{
  "info": {
    "name": "AI Project SOP API - Complete Collection",
    "description": "Complete API collection for AI Project Development SOP Understanding Platform\n\nIncludes:\n- Authentication endpoints\n- Project management\n- User stories, modules, features\n- Business rules & configurations\n- AI prompt generation\n\nAutomatic token management included!",
    "schema": "https://schema.getpostman.com/json/collection/v2.1.0/collection.json",
    "version": "1.0.0"
  },
  "variable": [
    {
      "key": "base_url",
      "value": "http://localhost:3000/api",
      "type": "string"
    },
    {
      "key": "access_token",
      "value": "",
      "type": "string"
    },
    {
      "key": "project_id",
      "value": "",
      "type": "string"
    },
    {
      "key": "user_story_id",
      "value": "",
      "type": "string"
    },
    {
      "key": "module_id",
      "value": "",
      "type": "string"
    }
  ],
  "item": [
    {
      "name": "🔐 Authentication",
      "item": [
        {
          "name": "1. Signup - Project Owner",
          "event": [
            {
              "listen": "test",
              "script": {
                "exec": [
                  "pm.test(\"Status code is 201\", function () {",
                  "    pm.response.to.have.status(201);",
                  "});",
                  "",
                  "pm.test(\"User created successfully\", function () {",
                  "    var jsonData = pm.response.json();",
                  "    pm.expect(jsonData.success).to.eql(true);",
                  "    pm.expect(jsonData.user).to.have.property('id');",
                  "});"
                ],
                "type": "text/javascript"
              }
            }
          ],
          "request": {
            "method": "POST",
            "header": [
              {
                "key": "Content-Type",
                "value": "application/json"
              }
            ],
            "body": {
              "mode": "raw",
              "raw": "{\n  \"email\": \"owner@example.com\",\n  \"password\": \"password123\",\n  \"name\": \"John Owner\",\n  \"role\": \"project_owner\"\n}"
            },
            "url": {
              "raw": "{{base_url}}/auth/signup",
              "host": ["{{base_url}}"],
              "path": ["auth", "signup"]
            },
            "description": "Create a new Project Owner account"
          },
          "response": []
        },
        {
          "name": "2. Signup - Vibe Engineer",
          "event": [
            {
              "listen": "test",
              "script": {
                "exec": [
                  "pm.test(\"Status code is 201\", function () {",
                  "    pm.response.to.have.status(201);",
                  "});",
                  "",
                  "pm.test(\"User created successfully\", function () {",
                  "    var jsonData = pm.response.json();",
                  "    pm.expect(jsonData.success).to.eql(true);",
                  "});"
                ],
                "type": "text/javascript"
              }
            }
          ],
          "request": {
            "method": "POST",
            "header": [
              {
                "key": "Content-Type",
                "value": "application/json"
              }
            ],
            "body": {
              "mode": "raw",
              "raw": "{\n  \"email\": \"engineer@example.com\",\n  \"password\": \"password123\",\n  \"name\": \"Jane Engineer\",\n  \"role\": \"vibe_engineer\"\n}"
            },
            "url": {
              "raw": "{{base_url}}/auth/signup",
              "host": ["{{base_url}}"],
              "path": ["auth", "signup"]
            },
            "description": "Create a new Vibe Engineer account"
          },
          "response": []
        },
        {
          "name": "3. Signin - Get Token",
          "event": [
            {
              "listen": "test",
              "script": {
                "exec": [
                  "pm.test(\"Status code is 200\", function () {",
                  "    pm.response.to.have.status(200);",
                  "});",
                  "",
                  "pm.test(\"Access token received\", function () {",
                  "    var jsonData = pm.response.json();",
                  "    pm.expect(jsonData.session).to.have.property('access_token');",
                  "    ",
                  "    // Save token to collection variable",
                  "    pm.collectionVariables.set('access_token', jsonData.session.access_token);",
                  "    console.log('✅ Token saved:', jsonData.session.access_token.substring(0, 20) + '...');",
                  "});"
                ],
                "type": "text/javascript"
              }
            }
          ],
          "request": {
            "method": "POST",
            "header": [
              {
                "key": "Content-Type",
                "value": "application/json"
              }
            ],
            "body": {
              "mode": "raw",
              "raw": "{\n  \"email\": \"owner@example.com\",\n  \"password\": \"password123\"\n}"
            },
            "url": {
              "raw": "{{base_url}}/auth/signin",
              "host": ["{{base_url}}"],
              "path": ["auth", "signin"]
            },
            "description": "Sign in and get JWT access token (automatically saved to collection variables)"
          },
          "response": []
        },
        {
          "name": "4. Get Current User",
          "event": [
            {
              "listen": "test",
              "script": {
                "exec": [
                  "pm.test(\"User profile retrieved\", function () {",
                  "    var jsonData = pm.response.json();",
                  "    pm.expect(jsonData.success).to.eql(true);",
                  "    pm.expect(jsonData.user).to.have.property('email');",
                  "    pm.expect(jsonData.user).to.have.property('role');",
                  "});"
                ],
                "type": "text/javascript"
              }
            }
          ],
          "request": {
            "method": "GET",
            "header": [
              {
                "key": "Authorization",
                "value": "Bearer {{access_token}}"
              }
            ],
            "url": {
              "raw": "{{base_url}}/auth/me",
              "host": ["{{base_url}}"],
              "path": ["auth", "me"]
            },
            "description": "Get current authenticated user profile"
          },
          "response": []
        },
        {
          "name": "5. Signout",
          "request": {
            "method": "POST",
            "header": [
              {
                "key": "Authorization",
                "value": "Bearer {{access_token}}"
              }
            ],
            "url": {
              "raw": "{{base_url}}/auth/signout",
              "host": ["{{base_url}}"],
              "path": ["auth", "signout"]
            },
            "description": "Sign out current user"
          },
          "response": []
        }
      ],
      "description": "Authentication endpoints - signup, signin, signout, get current user"
    },
    {
      "name": "📁 Projects",
      "item": [
        {
          "name": "1. Get All Projects",
          "event": [
            {
              "listen": "test",
              "script": {
                "exec": [
                  "pm.test(\"Projects retrieved\", function () {",
                  "    var jsonData = pm.response.json();",
                  "    pm.expect(jsonData.success).to.eql(true);",
                  "    pm.expect(jsonData.projects).to.be.an('array');",
                  "    ",
                  "    // Save first project ID if exists",
                  "    if (jsonData.projects.length > 0) {",
                  "        pm.collectionVariables.set('project_id', jsonData.projects[0].id);",
                  "        console.log('✅ Project ID saved:', jsonData.projects[0].id);",
                  "    }",
                  "});"
                ],
                "type": "text/javascript"
              }
            }
          ],
          "request": {
            "method": "GET",
            "header": [
              {
                "key": "Authorization",
                "value": "Bearer {{access_token}}"
              }
            ],
            "url": {
              "raw": "{{base_url}}/projects",
              "host": ["{{base_url}}"],
              "path": ["projects"]
            },
            "description": "Get all projects accessible to current user"
          },
          "response": []
        },
        {
          "name": "2. Create Project",
          "event": [
            {
              "listen": "test",
              "script": {
                "exec": [
                  "pm.test(\"Project created\", function () {",
                  "    pm.response.to.have.status(201);",
                  "    var jsonData = pm.response.json();",
                  "    pm.expect(jsonData.success).to.eql(true);",
                  "    pm.expect(jsonData.project).to.have.property('id');",
                  "    ",
                  "    // Save project ID",
                  "    pm.collectionVariables.set('project_id', jsonData.project.id);",
                  "    console.log('✅ New Project ID saved:', jsonData.project.id);",
                  "});"
                ],
                "type": "text/javascript"
              }
            }
          ],
          "request": {
            "method": "POST",
            "header": [
              {
                "key": "Content-Type",
                "value": "application/json"
              },
              {
                "key": "Authorization",
                "value": "Bearer {{access_token}}"
              }
            ],
            "body": {
              "mode": "raw",
              "raw": "{\n  \"name\": \"E-commerce Platform\",\n  \"description\": \"A modern e-commerce platform with user management and product catalog\"\n}"
            },
            "url": {
              "raw": "{{base_url}}/projects",
              "host": ["{{base_url}}"],
              "path": ["projects"]
            },
            "description": "Create a new project (Project Owner only)"
          },
          "response": []
        },
        {
          "name": "3. Get Project by ID",
          "request": {
            "method": "GET",
            "header": [
              {
                "key": "Authorization",
                "value": "Bearer {{access_token}}"
              }
            ],
            "url": {
              "raw": "{{base_url}}/projects/{{project_id}}",
              "host": ["{{base_url}}"],
              "path": ["projects", "{{project_id}}"]
            },
            "description": "Get specific project details"
          },
          "response": []
        },
        {
          "name": "4. Update Project",
          "request": {
            "method": "PUT",
            "header": [
              {
                "key": "Content-Type",
                "value": "application/json"
              },
              {
                "key": "Authorization",
                "value": "Bearer {{access_token}}"
              }
            ],
            "body": {
              "mode": "raw",
              "raw": "{\n  \"name\": \"Updated Project Name\",\n  \"description\": \"Updated description\",\n  \"completion_percentage\": 50\n}"
            },
            "url": {
              "raw": "{{base_url}}/projects/{{project_id}}",
              "host": ["{{base_url}}"],
              "path": ["projects", "{{project_id}}"]
            },
            "description": "Update project details"
          },
          "response": []
        },
        {
          "name": "5. Delete Project",
          "request": {
            "method": "DELETE",
            "header": [
              {
                "key": "Authorization",
                "value": "Bearer {{access_token}}"
              }
            ],
            "url": {
              "raw": "{{base_url}}/projects/{{project_id}}",
              "host": ["{{base_url}}"],
              "path": ["projects", "{{project_id}}"]
            },
            "description": "Delete a project (Project Owner only)"
          },
          "response": []
        }
      ],
      "description": "Project CRUD operations"
    },
    {
      "name": "📝 User Stories",
      "item": [
        {
          "name": "1. Get User Stories",
          "request": {
            "method": "GET",
            "header": [
              {
                "key": "Authorization",
                "value": "Bearer {{access_token}}"
              }
            ],
            "url": {
              "raw": "{{base_url}}/projects/{{project_id}}/user-stories",
              "host": ["{{base_url}}"],
              "path": ["projects", "{{project_id}}", "user-stories"]
            },
            "description": "Get all user stories for a project"
          },
          "response": []
        },
        {
          "name": "2. Save User Stories (Bulk)",
          "request": {
            "method": "POST",
            "header": [
              {
                "key": "Content-Type",
                "value": "application/json"
              },
              {
                "key": "Authorization",
                "value": "Bearer {{access_token}}"
              }
            ],
            "body": {
              "mode": "raw",
              "raw": "{\n  \"userStories\": [\n    {\n      \"id\": \"story-1\",\n      \"title\": \"User Login\",\n      \"user_role\": \"Customer\",\n      \"description\": \"As a customer, I want to login to my account so that I can access my orders\",\n      \"acceptance_criteria\": \"Given valid credentials, when user logs in, then they should be redirected to dashboard\",\n      \"priority\": \"High\",\n      \"status\": \"Not Started\",\n      \"module_id\": null\n    },\n    {\n      \"id\": \"story-2\",\n      \"title\": \"Product Search\",\n      \"user_role\": \"Customer\",\n      \"description\": \"As a customer, I want to search for products so that I can find items quickly\",\n      \"acceptance_criteria\": \"Given search term, when user searches, then relevant products are displayed\",\n      \"priority\": \"Medium\",\n      \"status\": \"Not Started\",\n      \"module_id\": null\n    }\n  ]\n}"
            },
            "url": {
              "raw": "{{base_url}}/projects/{{project_id}}/user-stories",
              "host": ["{{base_url}}"],
              "path": ["projects", "{{project_id}}", "user-stories"]
            },
            "description": "Save/replace all user stories for a project"
          },
          "response": []
        }
      ],
      "description": "User stories management"
    },
    {
      "name": "📦 Modules",
      "item": [
        {
          "name": "1. Get Modules",
          "request": {
            "method": "GET",
            "header": [
              {
                "key": "Authorization",
                "value": "Bearer {{access_token}}"
              }
            ],
            "url": {
              "raw": "{{base_url}}/projects/{{project_id}}/modules",
              "host": ["{{base_url}}"],
              "path": ["projects", "{{project_id}}", "modules"]
            },
            "description": "Get all modules for a project"
          },
          "response": []
        },
        {
          "name": "2. Save Modules (Bulk)",
          "request": {
            "method": "POST",
            "header": [
              {
                "key": "Content-Type",
                "value": "application/json"
              },
              {
                "key": "Authorization",
                "value": "Bearer {{access_token}}"
              }
            ],
            "body": {
              "mode": "raw",
              "raw": "{\n  \"modules\": [\n    {\n      \"id\": \"module-1\",\n      \"module_name\": \"User Authentication\",\n      \"description\": \"Handles user login, signup, and session management\",\n      \"priority\": \"High\",\n      \"business_impact\": \"Critical for platform security\",\n      \"dependencies\": \"Database, Email Service\",\n      \"status\": \"In Progress\"\n    },\n    {\n      \"id\": \"module-2\",\n      \"module_name\": \"Product Catalog\",\n      \"description\": \"Displays and manages product listings\",\n      \"priority\": \"High\",\n      \"business_impact\": \"Core business functionality\",\n      \"dependencies\": \"Database, Image Storage\",\n      \"status\": \"Not Started\"\n    }\n  ]\n}"
            },
            "url": {
              "raw": "{{base_url}}/projects/{{project_id}}/modules",
              "host": ["{{base_url}}"],
              "path": ["projects", "{{project_id}}", "modules"]
            },
            "description": "Save/replace all modules for a project"
          },
          "response": []
        }
      ],
      "description": "Project modules management"
    },
    {
      "name": "🔧 Features/Tasks",
      "item": [
        {
          "name": "1. Get Features",
          "request": {
            "method": "GET",
            "header": [
              {
                "key": "Authorization",
                "value": "Bearer {{access_token}}"
              }
            ],
            "url": {
              "raw": "{{base_url}}/projects/{{project_id}}/features",
              "host": ["{{base_url}}"],
              "path": ["projects", "{{project_id}}", "features"]
            },
            "description": "Get all features/tasks for a project"
          },
          "response": []
        },
        {
          "name": "2. Save Features (Bulk)",
          "request": {
            "method": "POST",
            "header": [
              {
                "key": "Content-Type",
                "value": "application/json"
              },
              {
                "key": "Authorization",
                "value": "Bearer {{access_token}}"
              }
            ],
            "body": {
              "mode": "raw",
              "raw": "{\n  \"features\": [\n    {\n      \"id\": \"feature-1\",\n      \"title\": \"Implement login form\",\n      \"description\": \"Create responsive login form with email/password fields\",\n      \"user_story_id\": \"story-1\",\n      \"module_id\": \"module-1\",\n      \"priority\": \"High\",\n      \"status\": \"In Progress\",\n      \"estimated_hours\": 8,\n      \"assignee\": \"developer@example.com\"\n    }\n  ]\n}"
            },
            "url": {
              "raw": "{{base_url}}/projects/{{project_id}}/features",
              "host": ["{{base_url}}"],
              "path": ["projects", "{{project_id}}", "features"]
            },
            "description": "Save/replace all features for a project"
          },
          "response": []
        }
      ],
      "description": "Features and tasks management"
    },
    {
      "name": "⚖️ Business Rules",
      "item": [
        {
          "name": "1. Get Business Rules",
          "request": {
            "method": "GET",
            "header": [
              {
                "key": "Authorization",
                "value": "Bearer {{access_token}}"
              }
            ],
            "url": {
              "raw": "{{base_url}}/projects/{{project_id}}/business-rules",
              "host": ["{{base_url}}"],
              "path": ["projects", "{{project_id}}", "business-rules"]
            },
            "description": "Get business rules configuration for a project"
          },
          "response": []
        },
        {
          "name": "2. Save Business Rules",
          "request": {
            "method": "POST",
            "header": [
              {
                "key": "Content-Type",
                "value": "application/json"
              },
              {
                "key": "Authorization",
                "value": "Bearer {{access_token}}"
              }
            ],
            "body": {
              "mode": "raw",
              "raw": "{\n  \"businessRules\": {\n    \"categories\": [\n      {\n        \"id\": \"data-integrity\",\n        \"name\": \"Data Integrity Rules\",\n        \"subcategories\": [\n          {\n            \"id\": \"uniqueness\",\n            \"name\": \"Uniqueness\",\n            \"example\": \"Ensure unique identifiers (user ID, email)\",\n            \"userRule\": \"All user emails must be unique\"\n          },\n          {\n            \"id\": \"mandatory-fields\",\n            \"name\": \"Mandatory Fields\",\n            \"example\": \"Fields that cannot be empty\",\n            \"userRule\": \"Name, email, and password are required\"\n          }\n        ]\n      }\n    ],\n    \"applyToAllProjects\": false,\n    \"specificModules\": []\n  }\n}"
            },
            "url": {
              "raw": "{{base_url}}/projects/{{project_id}}/business-rules",
              "host": ["{{base_url}}"],
              "path": ["projects", "{{project_id}}", "business-rules"]
            },
            "description": "Save business rules configuration (stored as JSONB)"
          },
          "response": []
        }
      ],
      "description": "Business rules configuration (JSONB storage)"
    },
    {
      "name": "⚡ Actions & Interactions",
      "item": [
        {
          "name": "1. Get Actions",
          "request": {
            "method": "GET",
            "header": [
              {
                "key": "Authorization",
                "value": "Bearer {{access_token}}"
              }
            ],
            "url": {
              "raw": "{{base_url}}/projects/{{project_id}}/actions",
              "host": ["{{base_url}}"],
              "path": ["projects", "{{project_id}}", "actions"]
            },
            "description": "Get actions/interactions configuration"
          },
          "response": []
        },
        {
          "name": "2. Save Actions",
          "request": {
            "method": "POST",
            "header": [
              {
                "key": "Content-Type",
                "value": "application/json"
              },
              {
                "key": "Authorization",
                "value": "Bearer {{access_token}}"
              }
            ],
            "body": {
              "mode": "raw",
              "raw": "{\n  \"actions\": {\n    \"categories\": [\n      {\n        \"id\": \"click-tap\",\n        \"name\": \"Click & Tap Actions\",\n        \"actions\": [\"Click\", \"Double-click\", \"Long press\", \"Tap\"]\n      },\n      {\n        \"id\": \"navigation\",\n        \"name\": \"Navigation\",\n        \"actions\": [\"Navigate to page\", \"Go back\", \"Scroll to section\"]\n      }\n    ],\n    \"selectedActions\": {\n      \"click-tap\": [\"Click\", \"Double-click\"],\n      \"navigation\": [\"Navigate to page\"]\n    },\n    \"applyToAllProjects\": false,\n    \"specificModules\": []\n  }\n}"
            },
            "url": {
              "raw": "{{base_url}}/projects/{{project_id}}/actions",
              "host": ["{{base_url}}"],
              "path": ["projects", "{{project_id}}", "actions"]
            },
            "description": "Save actions/interactions configuration (JSONB)"
          },
          "response": []
        }
      ],
      "description": "UI actions and interactions configuration"
    },
    {
      "name": "🎨 UI/UX Guidelines",
      "item": [
        {
          "name": "1. Get UI/UX Guidelines",
          "request": {
            "method": "GET",
            "header": [
              {
                "key": "Authorization",
                "value": "Bearer {{access_token}}"
              }
            ],
            "url": {
              "raw": "{{base_url}}/projects/{{project_id}}/uiux",
              "host": ["{{base_url}}"],
              "path": ["projects", "{{project_id}}", "uiux"]
            },
            "description": "Get UI/UX design guidelines"
          },
          "response": []
        },
        {
          "name": "2. Save UI/UX Guidelines",
          "request": {
            "method": "POST",
            "header": [
              {
                "key": "Content-Type",
                "value": "application/json"
              },
              {
                "key": "Authorization",
                "value": "Bearer {{access_token}}"
              }
            ],
            "body": {
              "mode": "raw",
              "raw": "{\n  \"guidelines\": {\n    \"branding\": {\n      \"primaryColor\": \"#00ff88\",\n      \"secondaryColor\": \"#0088ff\",\n      \"logo\": \"https://example.com/logo.png\"\n    },\n    \"typography\": {\n      \"headingFont\": \"Inter\",\n      \"bodyFont\": \"Roboto\",\n      \"fontSize\": \"16px\"\n    },\n    \"spacing\": {\n      \"baseUnit\": \"8px\",\n      \"containerPadding\": \"24px\"\n    }\n  }\n}"
            },
            "url": {
              "raw": "{{base_url}}/projects/{{project_id}}/uiux",
              "host": ["{{base_url}}"],
              "path": ["projects", "{{project_id}}", "uiux"]
            },
            "description": "Save UI/UX guidelines (JSONB)"
          },
          "response": []
        }
      ],
      "description": "UI/UX design guidelines configuration"
    },
    {
      "name": "💻 Tech Stack",
      "item": [
        {
          "name": "1. Get Tech Stack",
          "request": {
            "method": "GET",
            "header": [
              {
                "key": "Authorization",
                "value": "Bearer {{access_token}}"
              }
            ],
            "url": {
              "raw": "{{base_url}}/projects/{{project_id}}/tech-stack",
              "host": ["{{base_url}}"],
              "path": ["projects", "{{project_id}}", "tech-stack"]
            },
            "description": "Get technology stack configuration"
          },
          "response": []
        },
        {
          "name": "2. Save Tech Stack",
          "request": {
            "method": "POST",
            "header": [
              {
                "key": "Content-Type",
                "value": "application/json"
              },
              {
                "key": "Authorization",
                "value": "Bearer {{access_token}}"
              }
            ],
            "body": {
              "mode": "raw",
              "raw": "{\n  \"techStack\": {\n    \"frontend\": {\n      \"framework\": \"React\",\n      \"language\": \"TypeScript\",\n      \"styling\": \"Tailwind CSS\"\n    },\n    \"backend\": {\n      \"framework\": \"Express.js\",\n      \"language\": \"TypeScript\",\n      \"database\": \"PostgreSQL (Supabase)\"\n    },\n    \"deployment\": {\n      \"frontend\": \"Vercel\",\n      \"backend\": \"Railway\",\n      \"database\": \"Supabase Cloud\"\n    }\n  }\n}"
            },
            "url": {
              "raw": "{{base_url}}/projects/{{project_id}}/tech-stack",
              "host": ["{{base_url}}"],
              "path": ["projects", "{{project_id}}", "tech-stack"]
            },
            "description": "Save technology stack configuration (JSONB)"
          },
          "response": []
        }
      ],
      "description": "Technology stack configuration"
    },
    {
      "name": "📄 Documents",
      "item": [
        {
          "name": "1. Get Documents",
          "request": {
            "method": "GET",
            "header": [
              {
                "key": "Authorization",
                "value": "Bearer {{access_token}}"
              }
            ],
            "url": {
              "raw": "{{base_url}}/projects/{{project_id}}/documents",
              "host": ["{{base_url}}"],
              "path": ["projects", "{{project_id}}", "documents"]
            },
            "description": "Get project documents"
          },
          "response": []
        },
        {
          "name": "2. Save Documents",
          "request": {
            "method": "POST",
            "header": [
              {
                "key": "Content-Type",
                "value": "application/json"
              },
              {
                "key": "Authorization",
                "value": "Bearer {{access_token}}"
              }
            ],
            "body": {
              "mode": "raw",
              "raw": "{\n  \"documents\": {\n    \"requirements\": {\n      \"file_name\": \"requirements.pdf\",\n      \"url\": \"https://example.com/docs/requirements.pdf\",\n      \"uploaded_at\": \"2025-01-15T10:00:00Z\"\n    },\n    \"design_mockups\": {\n      \"file_name\": \"mockups.fig\",\n      \"url\": \"https://figma.com/file/xyz\",\n      \"uploaded_at\": \"2025-01-16T14:30:00Z\"\n    }\n  }\n}"
            },
            "url": {
              "raw": "{{base_url}}/projects/{{project_id}}/documents",
              "host": ["{{base_url}}"],
              "path": ["projects", "{{project_id}}", "documents"]
            },
            "description": "Save project documents metadata (JSONB)"
          },
          "response": []
        }
      ],
      "description": "Project documents management"
    },
    {
      "name": "🤖 AI Prompts",
      "item": [
        {
          "name": "1. Get All Prompts",
          "request": {
            "method": "GET",
            "header": [
              {
                "key": "Authorization",
                "value": "Bearer {{access_token}}"
              }
            ],
            "url": {
              "raw": "{{base_url}}/projects/{{project_id}}/prompts",
              "host": ["{{base_url}}"],
              "path": ["projects", "{{project_id}}", "prompts"]
            },
            "description": "Get all AI prompts generated for a project"
          },
          "response": []
        },
        {
          "name": "2. Generate AI Prompt",
          "event": [
            {
              "listen": "test",
              "script": {
                "exec": [
                  "pm.test(\"Prompt generated\", function () {",
                  "    pm.response.to.have.status(200);",
                  "    var jsonData = pm.response.json();",
                  "    pm.expect(jsonData.success).to.eql(true);",
                  "    pm.expect(jsonData.prompt).to.have.property('generated_prompt');",
                  "});"
                ],
                "type": "text/javascript"
              }
            }
          ],
          "request": {
            "method": "POST",
            "header": [
              {
                "key": "Content-Type",
                "value": "application/json"
              },
              {
                "key": "Authorization",
                "value": "Bearer {{access_token}}"
              }
            ],
            "body": {
              "mode": "raw",
              "raw": "{\n  \"projectId\": \"{{project_id}}\",\n  \"promptType\": \"full-project\",\n  \"context\": {\n    \"includeModules\": true,\n    \"includeUserStories\": true,\n    \"includeBusinessRules\": true\n  }\n}"
            },
            "url": {
              "raw": "{{base_url}}/prompts/generate",
              "host": ["{{base_url}}"],
              "path": ["prompts", "generate"]
            },
            "description": "Generate a new AI prompt based on project data"
          },
          "response": []
        },
        {
          "name": "3. Delete Prompt",
          "request": {
            "method": "DELETE",
            "header": [
              {
                "key": "Authorization",
                "value": "Bearer {{access_token}}"
              }
            ],
            "url": {
              "raw": "{{base_url}}/prompts/prompt-id-here",
              "host": ["{{base_url}}"],
              "path": ["prompts", "prompt-id-here"]
            },
            "description": "Delete a specific prompt"
          },
          "response": []
        }
      ],
      "description": "AI prompt generation and management"
    },
    {
      "name": "🔍 Utility Endpoints",
      "item": [
        {
          "name": "Health Check",
          "event": [
            {
              "listen": "test",
              "script": {
                "exec": [
                  "pm.test(\"API is running\", function () {",
                  "    pm.response.to.have.status(200);",
                  "    var jsonData = pm.response.json();",
                  "    pm.expect(jsonData.success).to.eql(true);",
                  "    pm.expect(jsonData.message).to.include('running');",
                  "});"
                ],
                "type": "text/javascript"
              }
            }
          ],
          "request": {
            "method": "GET",
            "header": [],
            "url": {
              "raw": "{{base_url}}/health",
              "host": ["{{base_url}}"],
              "path": ["health"]
            },
            "description": "Check if API is running (no auth required)"
          },
          "response": []
        },
        {
          "name": "API Root - Get Info",
          "request": {
            "method": "GET",
            "header": [],
            "url": {
              "raw": "http://localhost:3000/",
              "protocol": "http",
              "host": ["localhost"],
              "port": "3000",
              "path": [""]
            },
            "description": "Get API information and available endpoints"
          },
          "response": []
        }
      ],
      "description": "Utility endpoints for testing and monitoring"
    },
    {
      "name": "🔄 Complete Workflow Example",
      "item": [
        {
          "name": "Step 1: Signup",
          "event": [
            {
              "listen": "test",
              "script": {
                "exec": [
                  "pm.collectionVariables.set('test_email', 'workflow@example.com');"
                ]
              }
            }
          ],
          "request": {
            "method": "POST",
            "header": [
              {
                "key": "Content-Type",
                "value": "application/json"
              }
            ],
            "body": {
              "mode": "raw",
              "raw": "{\n  \"email\": \"workflow@example.com\",\n  \"password\": \"test123456\",\n  \"name\": \"Workflow Test User\",\n  \"role\": \"project_owner\"\n}"
            },
            "url": {
              "raw": "{{base_url}}/auth/signup",
              "host": ["{{base_url}}"],
              "path": ["auth", "signup"]
            }
          },
          "response": []
        },
        {
          "name": "Step 2: Signin",
          "event": [
            {
              "listen": "test",
              "script": {
                "exec": [
                  "var jsonData = pm.response.json();",
                  "pm.collectionVariables.set('access_token', jsonData.session.access_token);"
                ]
              }
            }
          ],
          "request": {
            "method": "POST",
            "header": [
              {
                "key": "Content-Type",
                "value": "application/json"
              }
            ],
            "body": {
              "mode": "raw",
              "raw": "{\n  \"email\": \"workflow@example.com\",\n  \"password\": \"test123456\"\n}"
            },
            "url": {
              "raw": "{{base_url}}/auth/signin",
              "host": ["{{base_url}}"],
              "path": ["auth", "signin"]
            }
          },
          "response": []
        },
        {
          "name": "Step 3: Create Project",
          "event": [
            {
              "listen": "test",
              "script": {
                "exec": [
                  "var jsonData = pm.response.json();",
                  "pm.collectionVariables.set('project_id', jsonData.project.id);"
                ]
              }
            }
          ],
          "request": {
            "method": "POST",
            "header": [
              {
                "key": "Content-Type",
                "value": "application/json"
              },
              {
                "key": "Authorization",
                "value": "Bearer {{access_token}}"
              }
            ],
            "body": {
              "mode": "raw",
              "raw": "{\n  \"name\": \"Workflow Test Project\",\n  \"description\": \"Testing complete workflow\"\n}"
            },
            "url": {
              "raw": "{{base_url}}/projects",
              "host": ["{{base_url}}"],
              "path": ["projects"]
            }
          },
          "response": []
        },
        {
          "name": "Step 4: Add Modules",
          "request": {
            "method": "POST",
            "header": [
              {
                "key": "Content-Type",
                "value": "application/json"
              },
              {
                "key": "Authorization",
                "value": "Bearer {{access_token}}"
              }
            ],
            "body": {
              "mode": "raw",
              "raw": "{\n  \"modules\": [\n    {\n      \"id\": \"mod-1\",\n      \"module_name\": \"Authentication\",\n      \"description\": \"User auth system\",\n      \"priority\": \"High\",\n      \"business_impact\": \"Critical\",\n      \"dependencies\": \"Database\",\n      \"status\": \"Not Started\"\n    }\n  ]\n}"
            },
            "url": {
              "raw": "{{base_url}}/projects/{{project_id}}/modules",
              "host": ["{{base_url}}"],
              "path": ["projects", "{{project_id}}", "modules"]
            }
          },
          "response": []
        },
        {
          "name": "Step 5: Add User Stories",
          "request": {
            "method": "POST",
            "header": [
              {
                "key": "Content-Type",
                "value": "application/json"
              },
              {
                "key": "Authorization",
                "value": "Bearer {{access_token}}"
              }
            ],
            "body": {
              "mode": "raw",
              "raw": "{\n  \"userStories\": [\n    {\n      \"id\": \"story-1\",\n      \"title\": \"User Registration\",\n      \"user_role\": \"New User\",\n      \"description\": \"As a new user, I want to create an account\",\n      \"acceptance_criteria\": \"User can signup with email and password\",\n      \"priority\": \"High\",\n      \"status\": \"Not Started\",\n      \"module_id\": \"mod-1\"\n    }\n  ]\n}"
            },
            "url": {
              "raw": "{{base_url}}/projects/{{project_id}}/user-stories",
              "host": ["{{base_url}}"],
              "path": ["projects", "{{project_id}}", "user-stories"]
            }
          },
          "response": []
        },
        {
          "name": "Step 6: Generate AI Prompt",
          "request": {
            "method": "POST",
            "header": [
              {
                "key": "Content-Type",
                "value": "application/json"
              },
              {
                "key": "Authorization",
                "value": "Bearer {{access_token}}"
              }
            ],
            "body": {
              "mode": "raw",
              "raw": "{\n  \"projectId\": \"{{project_id}}\",\n  \"promptType\": \"full-project\",\n  \"context\": {}\n}"
            },
            "url": {
              "raw": "{{base_url}}/prompts/generate",
              "host": ["{{base_url}}"],
              "path": ["prompts", "generate"]
            }
          },
          "response": []
        },
        {
          "name": "Step 7: View All Prompts",
          "request": {
            "method": "GET",
            "header": [
              {
                "key": "Authorization",
                "value": "Bearer {{access_token}}"
              }
            ],
            "url": {
              "raw": "{{base_url}}/projects/{{project_id}}/prompts",
              "host": ["{{base_url}}"],
              "path": ["projects", "{{project_id}}", "prompts"]
            }
          },
          "response": []
        }
      ],
      "description": "Complete workflow from signup to AI prompt generation"
    }
  ],
  "auth": {
    "type": "bearer",
    "bearer": [
      {
        "key": "token",
        "value": "{{access_token}}",
        "type": "string"
      }
    ]
  },
  "event": [
    {
      "listen": "prerequest",
      "script": {
        "type": "text/javascript",
        "exec": [
          "// This runs before every request",
          "console.log('🚀 Making request to:', pm.request.url.toString());"
        ]
      }
    },
    {
      "listen": "test",
      "script": {
        "type": "text/javascript",
        "exec": [
          "// This runs after every request",
          "console.log('📊 Response status:', pm.response.code);",
          "console.log('⏱️ Response time:', pm.response.responseTime + 'ms');"
        ]
      }
    }
  ]
}

